{"comment_text": "&gt; - Remote video surveillance<p>So the robbers wear masks and shoot&#x2F; paint over &#x2F; jam the video equipment.<p>&gt; - The driving algorithm will need to be capable of causing a 911 call to be made for various reasons, including that<p>So the robbers choose a section of road far away from the nearest police and otherwise conducive at making them difficult to follow.<p>&gt; - There is insurance for this kind of problem<p>If it gets to be too frequent of a problem, the insurance will become expensive enough that it will be easier just to keep a human around on more dangerous routes.", "author": "jjoonathan", "title": null, "url": null, "timestamp": 1431291822, "created_at": "2015-05-10T21:03:42.000Z", "comment_id": "9521308", "parent_id": 9521175, "story_title": "Autonomous truck cleared to drive on US roads for the first time", "story_id": 9521015, "story_url": "http://www.newscientist.com/article/dn27485-autonomous-truck-cleared-to-drive-on-us-roads-for-the-first-time.html#.VU-vqfSNFuE", "points": null}