{"comment_text": "Interesting, but I&#x27;d rather let SSH handle the SSH connection. Just add a command to the parameters, e.g. to run top:<p><pre><code>  ssh -t hostname top</code></pre>", "author": "andor", "title": null, "url": null, "timestamp": 1431278230, "created_at": "2015-05-10T17:17:10.000Z", "comment_id": "9520563", "parent_id": 9520381, "story_title": "Rtop \u2013 agentless sever monitoring tool (built with Go)", "story_id": 9520381, "story_url": "http://www.rtop-monitor.org/", "points": null}